clozer/__init__.py
clozer/infix.py
clozer/questions.py
clozer/questionvar.py
clozer/quiz.py
clozer/shapedquestionvar.py
clozer-0.0.1.dist-info/LICENSE
clozer-0.0.1.dist-info/METADATA
clozer-0.0.1.dist-info/WHEEL
clozer-0.0.1.dist-info/top_level.txt
clozer-0.0.1.dist-info/RECORD
