Metadata-Version: 2.1
Name: clozer
Version: 0.0.1
Summary: A tool to generate cloze quizes with random values.
Home-page: https://github.com/ndazeo/clozer
Author: Nicolás Dazeo
Author-email: ndazeo@gmail.com
License: UNKNOWN
Project-URL: Bug Tracker, https://github.com/ndazeo/clozer/issues
Platform: UNKNOWN
Classifier: Programming Language :: Python :: 3
Classifier: License :: OSI Approved :: MIT License
Classifier: Operating System :: OS Independent
Requires-Python: >=3.6
